python_install_directives/__init__.py
python_install_directives/__main__.py
python_install_directives/api.py
install_directives-1.0.0.dist-info/LICENSE
install_directives-1.0.0.dist-info/METADATA
install_directives-1.0.0.dist-info/WHEEL
install_directives-1.0.0.dist-info/entry_points.txt
install_directives-1.0.0.dist-info/RECORD
