Metadata-Version: 2.1
Name: install-directives
Version: 1.0.0
Summary: Useful for doing pip post-install/uninstall things
Home-page: https://github.com/zmarffy/install-directives
License: MIT
Author: Zeke Marffy
Author-email: zmarffy@me.com
Requires-Python: >=3.8.1,<4.0.0
Classifier: License :: OSI Approved :: MIT License
Classifier: Programming Language :: Python :: 3
Classifier: Programming Language :: Python :: 3.9
Classifier: Programming Language :: Python :: 3.10
Classifier: Programming Language :: Python :: 3.11
Requires-Dist: zmtools (>=3.0.0,<4.0.0)
Project-URL: Repository, https://github.com/zmarffy/install-directives
